datamanipylator/__init__.py
datamanipylator/algorithm.py
datamanipylator/analyzers.py
datamanipylator/data.py
datamanipylator/decorators.py
datamanipylator/exceptions.py
datamanipylator/utils.py
datamanipylator-1.0.0.dist-info/LICENSE
datamanipylator-1.0.0.dist-info/METADATA
datamanipylator-1.0.0.dist-info/WHEEL
datamanipylator-1.0.0.dist-info/top_level.txt
datamanipylator-1.0.0.dist-info/RECORD
