Metadata-Version: 2.2
Name: datamanipylator
Version: 1.0.0
Summary: Library to process data
Home-page: https://github.com/jose-caballero/manipylator
Author: Jose Caballero
Author-email: jcaballero.hep@gmail.com
Classifier: Programming Language :: Python :: 3.6
Classifier: License :: OSI Approved :: Apache Software License
Classifier: Operating System :: OS Independent
Requires-Python: >=3.6
License-File: LICENSE
Dynamic: author
Dynamic: author-email
Dynamic: classifier
Dynamic: description
Dynamic: description-content-type
Dynamic: home-page
Dynamic: requires-python
Dynamic: summary
